napkinxc/__init__.py
napkinxc/_napkinxc.cpython-310-x86_64-linux-gnu.so
napkinxc/datasets.py
napkinxc/metrics.py
napkinxc/models.py
napkinxc-0.7.2.dist-info/METADATA
napkinxc-0.7.2.dist-info/WHEEL
napkinxc-0.7.2.dist-info/top_level.txt
napkinxc-0.7.2.dist-info/RECORD
napkinxc-0.7.2.dist-info/licenses/LICENSE.md
