Metadata-Version: 2.1
Name: napkinxc
Version: 0.7.2
Summary: napkinXC is an extremely simple and fast library for extreme multi-class and multi-label classification.
Home-page: https://github.com/mwydmuch/napkinXC
Author: Marek Wydmuch
Author-email: mwydmuch@cs.put.poznan.pl
Maintainer: Marek Wydmuch
Maintainer-email: mwydmuch@cs.put.poznan.pl
License: MIT License
Keywords: machine learning,extreme classification,multi-class classification,multi-label classification,classification
Platform: Linux
Platform: MacOS
Platform: Windows
Classifier: Development Status :: 4 - Beta
Classifier: Operating System :: POSIX :: Linux
Classifier: Operating System :: MacOS
Classifier: Operating System :: Microsoft :: Windows
Classifier: Intended Audience :: Developers
Classifier: Intended Audience :: Science/Research
Classifier: Topic :: Scientific/Engineering :: Artificial Intelligence
Classifier: License :: OSI Approved :: MIT License
Classifier: Programming Language :: Python :: 3.10
Classifier: Programming Language :: Python :: 3.11
Classifier: Programming Language :: Python :: 3.12
Classifier: Programming Language :: Python :: 3.13
Classifier: Programming Language :: Python :: 3.14
Requires-Python: >=3.10.0,<3.15
License-File: LICENSE.md
Requires-Dist: numpy
Requires-Dist: scipy
Requires-Dist: gdown
